src/__init__.py
src/cli.py
src/config.py
src/configs.py
src/engine.py
src/molecule.py
src/runner.py
src/slurm.py
orcastrator-3.4.2.dist-info/METADATA
orcastrator-3.4.2.dist-info/WHEEL
orcastrator-3.4.2.dist-info/entry_points.txt
orcastrator-3.4.2.dist-info/licenses/LICENSE
orcastrator-3.4.2.dist-info/RECORD
