Metadata-Version: 2.4
Name: orcastrator
Version: 3.4.2
Summary: ORCA high-throughput pipeline orchestrator
License-Expression: MIT
License-File: LICENSE
Requires-Python: >=3.11
Requires-Dist: click>=8.1.8
Requires-Dist: jinja2>=3.1.6
Requires-Dist: loguru>=0.7.3
Requires-Dist: pydantic>=2.11.7
Requires-Dist: tomli>=2.0.1
